adsGenericFunctions/__init__.py
adsGenericFunctions/dataFactory.py
adsGenericFunctions/dbMssql.py
adsGenericFunctions/dbPgsql.py
adsGenericFunctions/demo/_demo.py
adsGenericFunctions/demo/dataset_deduplicate.py
adsGenericFunctions/demo/dataset_file.py
adsGenericFunctions/demo/dataset_join.py
adsGenericFunctions/demo/dataset_sort.py
adsGenericFunctions/demo/dataset_transform.py
adsGenericFunctions/demo/demo.py
adsGenericFunctions/demo/demo_logger_timer.py
adsGenericFunctions/demo/demo_pipeline_1.py
adsGenericFunctions/demo/demo_pipeline_2_tableau.py
adsGenericFunctions/demo/demo_pipeline_3_destinations.py
adsGenericFunctions/demo/demo_pipeline_yield.py
adsGenericFunctions/demo/demo_request_insertion.py
adsGenericFunctions/demo/demo_wait_file.py
adsGenericFunctions/demo/example_data.csv
adsGenericFunctions/demo/log.txt
adsGenericFunctions/global_config.py
adsGenericFunctions/logger.py
adsGenericFunctions/pipeline.py
adsGenericFunctions/timer.py
adsGenericFunctions/to_sort/email.py
adsGenericFunctions/to_sort/env.py
adsGenericFunctions/wait_file.py
adsgenericfunctions-0.2.53.dist-info/METADATA
adsgenericfunctions-0.2.53.dist-info/WHEEL
adsgenericfunctions-0.2.53.dist-info/RECORD
