Metadata-Version: 2.1
Name: adsGenericFunctions
Version: 0.2.53
Summary: Generic functions
License: MIT
Author: Olivier Siguré
Author-email: olivier.sigure@alchimiedatasolutions.com
Requires-Python: >=3.09,<4.0
Classifier: License :: OSI Approved :: MIT License
Classifier: Programming Language :: Python :: 3
Classifier: Programming Language :: Python :: 3.9
Classifier: Programming Language :: Python :: 3.10
Classifier: Programming Language :: Python :: 3.11
Classifier: Programming Language :: Python :: 3.12
Requires-Dist: psycopg2-binary (>=2.9.5,<3.0.0)
Requires-Dist: python-http-client (==3.3.7)
Requires-Dist: sendgrid (==6.10.0)
Requires-Dist: starkbank-ecdsa (==2.2.0)
